radicale_imaps/__init__.py
radicale_imaps-0.1.1.dist-info/LICENSE
radicale_imaps-0.1.1.dist-info/METADATA
radicale_imaps-0.1.1.dist-info/WHEEL
radicale_imaps-0.1.1.dist-info/top_level.txt
radicale_imaps-0.1.1.dist-info/RECORD
