Metadata-Version: 2.1
Name: radicale-imaps
Version: 0.1.1
Summary: Radicale IMAPs authentication plugin
Home-page: https://github.com/reind33r/radicale-imaps
Author: Louis Guidez
Author-email: louis@hostux.fr
License: LICENSE
Platform: UNKNOWN
Classifier: Development Status :: 5 - Production/Stable
Classifier: Environment :: Console
Classifier: License :: OSI Approved :: GNU General Public License v3 (GPLv3)
Classifier: Operating System :: OS Independent
Classifier: Programming Language :: Python :: 3 :: Only
Classifier: Programming Language :: Python :: 3.4
Classifier: Programming Language :: Python :: 3.5
Classifier: Programming Language :: Python :: 3.6
Classifier: Programming Language :: Python :: 3.7
Requires-Dist: radicale
